tmm_fast/__init__.py
tmm_fast/plotting_helper.py
tmm_fast/tmm_fast_torch.py
tmm_fast/vectorized_tmm_dispersive_multistack.py
tmm_fast/gym_multilayerthinfilm/LICENSE
tmm_fast/gym_multilayerthinfilm/README.md
tmm_fast/gym_multilayerthinfilm/__init__.py
tmm_fast/gym_multilayerthinfilm/gym_class.py
tmm_fast/gym_multilayerthinfilm/gym_environment_example.py
tmm_fast/gym_multilayerthinfilm/gym_multilayerthinfilm.yml
tmm_fast/gym_multilayerthinfilm/utils.py
tmm_fast/materials/nAu.txt
tmm_fast/materials/nNb2O5.txt
tmm_fast/materials/nSiO2.txt
tmm_fast/misc/tmm_structure.svg
tmm_fast-0.2.1.dist-info/LICENSE
tmm_fast-0.2.1.dist-info/METADATA
tmm_fast-0.2.1.dist-info/WHEEL
tmm_fast-0.2.1.dist-info/top_level.txt
tmm_fast-0.2.1.dist-info/RECORD
