Metadata-Version: 2.1
Name: tmm-fast
Version: 0.2.1
Summary: tmm_fast is a lightweight package to speed up optical planar multilayer thin-film device computation.
Author: Heribert Wankerl
Author-email: Alexander Luce <alexander.luce@ams-osram.com>
License: MIT
Keywords: one,two
Classifier: Programming Language :: Python :: 3
Requires-Python: >=3.7
License-File: LICENSE
Requires-Dist: numpy
Requires-Dist: torch >1.9
Requires-Dist: matplotlib
Requires-Dist: gymnasium
